array_like_generic/__init__.py
array_like_generic-0.0.1.dist-info/LICENSE
array_like_generic-0.0.1.dist-info/METADATA
array_like_generic-0.0.1.dist-info/WHEEL
array_like_generic-0.0.1.dist-info/top_level.txt
array_like_generic-0.0.1.dist-info/RECORD
