Metadata-Version: 2.1
Name: array_like_generic
Version: 0.0.1
Summary: A tiny project that contains array like functions.
Author-email: Caewinix <Caewinix@yeah.net>
Project-URL: Homepage, https://github.com/Caewinix/array_like_generic
Project-URL: Bug Tracker, https://github.com/Caewinix/array_like_generic/issues
Classifier: Programming Language :: Python :: 3
Classifier: License :: OSI Approved :: MIT License
Classifier: Operating System :: OS Independent
Requires-Python: >=3.7
License-File: LICENSE
